MANIFEST.in
setup.py
gameHook_1_50/1.png
gameHook_1_50/10.png
gameHook_1_50/11.png
gameHook_1_50/12.png
gameHook_1_50/13.png
gameHook_1_50/14.png
gameHook_1_50/15.png
gameHook_1_50/16.png
gameHook_1_50/17.png
gameHook_1_50/18.png
gameHook_1_50/19.png
gameHook_1_50/2.png
gameHook_1_50/20.png
gameHook_1_50/21.png
gameHook_1_50/22.png
gameHook_1_50/23.png
gameHook_1_50/24.png
gameHook_1_50/25.png
gameHook_1_50/26.png
gameHook_1_50/27.png
gameHook_1_50/28.png
gameHook_1_50/29.png
gameHook_1_50/3.png
gameHook_1_50/30.png
gameHook_1_50/31.png
gameHook_1_50/32.png
gameHook_1_50/33.png
gameHook_1_50/34.png
gameHook_1_50/35.png
gameHook_1_50/36.png
gameHook_1_50/37.png
gameHook_1_50/38.png
gameHook_1_50/39.png
gameHook_1_50/4.png
gameHook_1_50/40.png
gameHook_1_50/41.png
gameHook_1_50/42.png
gameHook_1_50/43.png
gameHook_1_50/44.png
gameHook_1_50/45.png
gameHook_1_50/46.png
gameHook_1_50/47.png
gameHook_1_50/48.png
gameHook_1_50/49.png
gameHook_1_50/5.png
gameHook_1_50/50.png
gameHook_1_50/6.png
gameHook_1_50/7.png
gameHook_1_50/8.png
gameHook_1_50/9.png
gameHook_1_50/__init__.py
gameHook_1_50.egg-info/PKG-INFO
gameHook_1_50.egg-info/SOURCES.txt
gameHook_1_50.egg-info/dependency_links.txt
gameHook_1_50.egg-info/entry_points.txt
gameHook_1_50.egg-info/top_level.txt