Metadata-Version: 1.0
Name: gameHook-1-50
Version: 1.0.0
Summary: game tool for 1-50 auto-click
Home-page: https://github.com/funny4875/1-50
Author: funny4875
Author-email: funny4875@gmail.com
License: MIT
Platform: UNKNOWN
